pycorruptor/__init__.py
pycorruptor/__version__.py
pycorruptor/corrupt.py
pycorruptor/tests/__init__.py
pycorruptor-0.0.4.dist-info/LICENSE
pycorruptor-0.0.4.dist-info/METADATA
pycorruptor-0.0.4.dist-info/WHEEL
pycorruptor-0.0.4.dist-info/top_level.txt
pycorruptor-0.0.4.dist-info/RECORD
