Metadata-Version: 2.1
Name: pycorruptor
Version: 0.0.4
Summary: A Python Toolbox for Data Corruption
Home-page: https://github.com/WenjieDu/PyCorruptor
Download-URL: https://github.com/WenjieDu/PyCorruptor/archive/main.zip
Author: Wenjie Du
Author-email: wenjay.du@gmail.com
License: GPL-3.0
Keywords: missing data,missing values,data corruption,incomplete data,partial observation,data mining
Platform: UNKNOWN
License-File: LICENSE
Requires-Dist: numpy
Requires-Dist: scikit-learn
Requires-Dist: pandas
